Metadata-Version: 2.1
Name: odoo14-addon-base-business-document-import
Version: 14.0.3.2.0
Summary: Provides technical tools to import sale orders or supplier invoices
Home-page: https://github.com/OCA/edi
Author: Akretion, Nicolas JEUDY, Odoo Community Association (OCA)
Author-email: support@odoo-community.org
License: AGPL-3
Platform: UNKNOWN
Classifier: Programming Language :: Python
Classifier: Framework :: Odoo
Classifier: Framework :: Odoo :: 14.0
Classifier: License :: OSI Approved :: GNU Affero General Public License v3
Requires-Python: >=3.6
Requires-Dist: odoo14-addon-account-tax-unece
Requires-Dist: odoo14-addon-pdf-helper
Requires-Dist: odoo14-addon-uom-unece
Requires-Dist: odoo <14.1dev,>=14.0a
